{
  "airingid": "RADS1007262200015522",
  "seasonnumber": "1",
  "seasonitemnumber": "52",
  "seriesid": "100000000001182633",
  "id": "05e603d0e0a1d478d3768b948d3c427f0bd40b2e",
  "collectionid": "",
  "seofriendlyurl": "/video/ben-10-classic/and-then-there-was-ben-episode.html",
  "seasonepisodenumber": "52",
  "title": "And Then There Was Ben",
  "episodenumber": "52",
  "type": "fullepisode",
  "active": true,
  "description": "Professor Paradox unites the good Bens from across all dimensions to take on Vilgax, Eon, and the evil Bens in the ultimate showdown!",
  "duration": 1346,
  "freewheelid": "cn-2005816",
  "isclip": false,
  "typesort": "1",
  "tvratingcode": "TV-Y7-FV",
  "seriestitleid": "100000000001182633",
  "seriesname": "Ben 10 Classic",
  "originalpremieredate": "2022-07-29T09:00:00.000Z",
  "pubdate": "2022-07-29T09:00:00.000Z",
  "expdate": "2022-09-02T09:00:00.000Z",
  "thumbnailurl": "https://i.cartoonnetwork.com/orchestrator/2005816_009_640x360.jpg",
  "authtype": "auth",
  "webflags": "",
  "tags": "ben 10 - classic",
  "titleid": "2005816",
  "titletype": "Episode",
  "bannertext": "",
  "originalseriesid": "871368",
  "originalseriesname": "Ben 10: Omniverse",
  "hasparent": false,
  "originalpremieredateasmilliseconds": "1659085200000",
  "pubdateasmilliseconds": "1659085200000",
  "expdateasmilliseconds": "1662109200000",
  "mediaid": "05e603d0e0a1d478d3768b948d3c427f0bd40b2e",
  "isunlockedfullepisode": false,
  "ismultipropertycollection": true,
  "clipsonly": false,
  "includeshortform": false
}