{
  "airingid": "RADS1004142100089628",
  "seasonnumber": "1",
  "seasonitemnumber": "6",
  "seriesid": "2117352",
  "id": "8ef5f9a76fcc4084e814822868b94eecb7c3768d",
  "collectionid": "",
  "seofriendlyurl": "/video/mega-man/blaze-of-glory-episode.html",
  "seasonepisodenumber": "6",
  "title": "Blaze of Glory",
  "episodenumber": "6",
  "type": "fullepisode",
  "active": true,
  "description": "Mega Man and Suna must overcome a sibling dispute over what to do on their day off in order to stop Fire Man from overheating the city.",
  "duration": 667,
  "freewheelid": "cn-2117358",
  "isclip": false,
  "typesort": "1",
  "tvratingcode": "TV-Y7-FV",
  "seriestitleid": "2117352",
  "seriesname": "Mega Man",
  "originalpremieredate": "2018-08-19T10:30:00.000Z",
  "pubdate": "2021-04-30T09:01:00.000Z",
  "expdate": "2021-08-24T09:00:00.000Z",
  "thumbnailurl": "https://i.cartoonnetwork.com/orchestrator/2117358_003_640x360.jpg",
  "authtype": "auth",
  "webflags": "",
  "tags": "",
  "titleid": "2117358",
  "titletype": "Episode",
  "bannertext": "",
  "originalseriesid": "2117352",
  "originalseriesname": "Mega Man",
  "hasparent": false,
  "originalpremieredateasmilliseconds": "1534674600000",
  "pubdateasmilliseconds": "1619773260000",
  "expdateasmilliseconds": "1629795600000",
  "mediaid": "8ef5f9a76fcc4084e814822868b94eecb7c3768d",
  "isunlockedfullepisode": false,
  "ismultipropertycollection": false,
  "clipsonly": false,
  "includeshortform": false
}