{
  "airingid": "RADS1001071900059164",
  "seasonnumber": "1",
  "seasonitemnumber": "",
  "seriesid": "2170837",
  "id": "dc95770b856d31856275d39a9058d292fa8fb547",
  "collectionid": "",
  "seofriendlyurl": "/video/bakugan/bakugan-beyond-the-brawl-snack-attack-episode.html",
  "seasonepisodenumber": "",
  "title": "Bakugan: Beyond the Brawl - Snack Attack",
  "episodenumber": "",
  "type": "short",
  "active": true,
  "description": "Two Awesome One Bakugan battle over a bag of chips.",
  "duration": 96,
  "freewheelid": "cn-2188510",
  "isclip": false,
  "typesort": "2",
  "tvratingcode": "TV-Y7-FV",
  "seriestitleid": "2170837",
  "seriesname": "Bakugan: Battle Planet",
  "originalpremieredate": "2019-01-08T10:00:00.000Z",
  "pubdate": "2019-01-08T10:00:00.000Z",
  "expdate": "2022-12-23T04:59:59.000Z",
  "thumbnailurl": "https://i.cartoonnetwork.com/orchestrator/2188510_001_640x360.jpg",
  "authtype": "unauth",
  "webflags": "",
  "tags": "shorts",
  "titleid": "2188510",
  "titletype": "Element",
  "bannertext": "",
  "originalseriesid": "2170837",
  "originalseriesname": "Bakugan: Battle Planet",
  "hasparent": false,
  "originalpremieredateasmilliseconds": "1546941600000",
  "pubdateasmilliseconds": "1546941600000",
  "expdateasmilliseconds": "1671771599000",
  "mediaid": "dc95770b856d31856275d39a9058d292fa8fb547",
  "isunlockedfullepisode": false,
  "ismultipropertycollection": false,
  "clipsonly": false,
  "includeshortform": false
}