{
  "airingid": "RADS1006012100001984",
  "seasonnumber": "2",
  "seasonitemnumber": "13",
  "seriesid": "1000000000070392",
  "id": "afadf9700348bab9c30d56e0d6f74ec43b82f6cc",
  "collectionid": "",
  "seofriendlyurl": "/video/craig-of-the-creek/cousin-of-the-creek-episode.html",
  "seasonepisodenumber": "13",
  "title": "Cousin of the Creek",
  "episodenumber": "13",
  "type": "fullepisode",
  "active": true,
  "description": "Craig takes his cousin, Bryson, to the Creek, and accidentally starts a water balloon war.",
  "duration": 677,
  "freewheelid": "cn-2191364",
  "isclip": false,
  "typesort": "1",
  "tvratingcode": "TV-Y7",
  "seriestitleid": "1000000000070392",
  "seriesname": "Pride Month",
  "originalpremieredate": "2019-08-03T13:00:00.000Z",
  "pubdate": "2021-06-11T09:00:00.000Z",
  "expdate": "2021-07-02T09:00:00.000Z",
  "thumbnailurl": "https://i.cartoonnetwork.com/orchestrator/2191364_004_640x360.jpg",
  "authtype": "auth",
  "webflags": "",
  "tags": "pride month",
  "titleid": "2191364",
  "titletype": "Episode",
  "bannertext": "",
  "originalseriesid": "2132940",
  "originalseriesname": "Craig of the Creek",
  "hasparent": false,
  "originalpremieredateasmilliseconds": "1564837200000",
  "pubdateasmilliseconds": "1623402000000",
  "expdateasmilliseconds": "1625216400000",
  "mediaid": "afadf9700348bab9c30d56e0d6f74ec43b82f6cc",
  "isunlockedfullepisode": false,
  "ismultipropertycollection": true,
  "clipsonly": false,
  "includeshortform": true
}