{
  "airingid": "RADS1003032000069132",
  "seasonnumber": "4",
  "seasonitemnumber": "12",
  "seriesid": "2085313",
  "id": "c3ee048a6f66130ffb3b7650ecf16e94e6664bcc",
  "collectionid": "",
  "seofriendlyurl": "/video/ben-10/mud-on-the-run-episode.html",
  "seasonepisodenumber": "12",
  "title": "Mud on the Run",
  "episodenumber": "12",
  "type": "fullepisode",
  "active": true,
  "description": "Ben gets a tough lesson on knowing his limits when he competes in a grueling obstacle race, made even worse by the Weatherheads!",
  "duration": 676,
  "freewheelid": "cn-2194868",
  "isclip": false,
  "typesort": "1",
  "tvratingcode": "TV-Y7-FV",
  "seriestitleid": "2085313",
  "seriesname": "Ben 10",
  "originalpremieredate": "2020-03-01T15:00:00.000Z",
  "pubdate": "2020-04-13T09:00:00.000Z",
  "expdate": "2022-01-01T04:59:59.000Z",
  "thumbnailurl": "https://i.cartoonnetwork.com/orchestrator/2194868_006_640x360.jpg",
  "authtype": "auth",
  "webflags": "",
  "tags": "",
  "titleid": "2194868",
  "titletype": "Episode",
  "bannertext": "",
  "originalseriesid": "2085313",
  "originalseriesname": "Ben 10",
  "hasparent": false,
  "originalpremieredateasmilliseconds": "1583074800000",
  "pubdateasmilliseconds": "1586768400000",
  "expdateasmilliseconds": "1641013199000",
  "mediaid": "c3ee048a6f66130ffb3b7650ecf16e94e6664bcc",
  "isunlockedfullepisode": false,
  "ismultipropertycollection": false,
  "clipsonly": false,
  "includeshortform": false
}