{
  "airingid": "RADS1012042000050275",
  "seasonnumber": "3",
  "seasonitemnumber": "39",
  "seriesid": "2167202",
  "id": "f753577157154d4ec7d04443af162c9b71688099",
  "collectionid": "",
  "seofriendlyurl": "/video/transformers-cyberverse/journey-to-the-valley-of-repugnus-part-1-episode.html",
  "seasonepisodenumber": "39",
  "title": "Journey to the Valley of Repugnus Part 1",
  "episodenumber": "39",
  "type": "fullepisode",
  "active": true,
  "description": "Bumblebee and Grimlock are separated as they search the depths of Cybertron for another of Windblade's psychic shards, encountering the Monsterbots and the Energon Masters.",
  "duration": 319,
  "freewheelid": "cn-2215401",
  "isclip": false,
  "typesort": "1",
  "tvratingcode": "TV-Y7-FV",
  "seriestitleid": "2167202",
  "seriesname": "Transformers Cyberverse",
  "originalpremieredate": "2020-12-25T10:00:00.000Z",
  "pubdate": "2020-12-25T10:00:00.000Z",
  "expdate": "2021-03-15T03:59:59.000Z",
  "thumbnailurl": "https://i.cartoonnetwork.com/orchestrator/2215401_009_640x360.jpg",
  "authtype": "unauth",
  "webflags": "",
  "tags": "unauth",
  "titleid": "2215401",
  "titletype": "Element",
  "bannertext": "LATEST EPISODE",
  "originalseriesid": "2167202",
  "originalseriesname": "Transformers Cyberverse",
  "hasparent": false,
  "originalpremieredateasmilliseconds": "1608890400000",
  "pubdateasmilliseconds": "1608890400000",
  "expdateasmilliseconds": "1615780799000",
  "mediaid": "f753577157154d4ec7d04443af162c9b71688099",
  "isunlockedfullepisode": true,
  "ismultipropertycollection": false,
  "clipsonly": false,
  "includeshortform": false
}