{
  "airingid": "RADS1008292200023599",
  "seasonnumber": "6",
  "seasonitemnumber": "22",
  "seriesid": "10000000000",
  "id": "d635ac86b6ff3d593e251dab98b17b9efdab0833",
  "collectionid": "",
  "seofriendlyurl": "/video/teen-titans-go/nbts-2-chapter-five-episode.html",
  "seasonepisodenumber": "22",
  "title": "NBTS 2: Chapter Five",
  "episodenumber": "22",
  "type": "fullepisode",
  "active": true,
  "description": "The Titans use to the stems to summon BER, but will it be enough to stop Ultralak?",
  "duration": 689,
  "freewheelid": "cn-2215232",
  "isclip": false,
  "typesort": "1",
  "tvratingcode": "TV-PG",
  "seriestitleid": "10000000000",
  "seriesname": "Unlocked",
  "originalpremieredate": "2022-09-02T09:00:00.000Z",
  "pubdate": "2022-09-02T09:00:00.000Z",
  "expdate": "2022-09-15T03:59:00.000Z",
  "thumbnailurl": "https://i.cartoonnetwork.com/orchestrator/2215232_003_640x360.jpg",
  "authtype": "unauth",
  "webflags": "",
  "tags": "unauth",
  "titleid": "2215232",
  "titletype": "Episode",
  "bannertext": "",
  "originalseriesid": "2000349",
  "originalseriesname": "Teen Titans Go!",
  "hasparent": false,
  "originalpremieredateasmilliseconds": "1662109200000",
  "pubdateasmilliseconds": "1662109200000",
  "expdateasmilliseconds": "1663214340000",
  "mediaid": "d635ac86b6ff3d593e251dab98b17b9efdab0833",
  "isunlockedfullepisode": true,
  "ismultipropertycollection": true,
  "clipsonly": false,
  "includeshortform": false
}