[
    {
        "airingid": "RADS1012302500076981",
        "seasonnumber": "1",
        "seasonitemnumber": "30",
        "seriesid": "2503122",
        "id": "6ba92bdce6ec1ec7b8026cd9789e9197c5380c42",
        "collectionid": "",
        "seofriendlyurl": "/video/barney's-world/too-far-episode.html",
        "seasonepisodenumber": "30",
        "title": "Too Far",
        "episodenumber": "30",
        "type": "fullepisode",
        "active": true,
        "description": "When Baby Bop's playful teasing starts bothering Mel, Barney arranges a trip to the Castleverse where their adventure motivates Mel to finally speak up for herself.",
        "duration": 670,
        "freewheelid": "cn-2503175",
        "isclip": false,
        "typesort": "1",
        "tvratingcode": "TV-Y",
        "seriestitleid": "2503122",
        "seriesname": "Barney's World",
        "originalpremieredate": "2026-01-01T05:00:00.000Z",
        "pubdate": "2026-01-01T05:00:00.000Z",
        "expdate": "2026-11-26T04:59:00.000Z",
        "thumbnailurl": "https://i.cartoonnetwork.com/orchestrator/2503175_002_640x360.jpg",
        "authtype": "auth",
        "webflags": "",
        "tags": "cartoonito",
        "titleid": "2503175",
        "titletype": "Episode",
        "bannertext": "LATEST EPISODE",
        "originalseriesid": "2503122",
        "originalseriesname": "Barney's World",
        "hasparent": false,
        "originalpremieredateasmilliseconds": "1767243600000",
        "pubdateasmilliseconds": "1767243600000",
        "expdateasmilliseconds": "1795669140000",
        "mediaid": "6ba92bdce6ec1ec7b8026cd9789e9197c5380c42",
        "isunlockedfullepisode": false,
        "ismultipropertycollection": false,
        "clipsonly": false,
        "includeshortform": true
    },
    {
        "airingid": "RADS1012302500076973",
        "seasonnumber": "1",
        "seasonitemnumber": "26",
        "seriesid": "2503122",
        "id": "70da38da2a9b34632706af0353e8c08b6fb2e4cc",
        "collectionid": "",
        "seofriendlyurl": "/video/barney's-world/finders-not-keepers-episode.html",
        "seasonepisodenumber": "26",
        "title": "Finders Not Keepers",
        "episodenumber": "26",
        "type": "fullepisode",
        "active": true,
        "description": "When Mel discovers the sunglasses she found belong to Grady, she still wants to keep them. Barney creates a high-seas adventure, where Mel realizes she's acting like a pirate taking what doesn't belong to her and returns the glasses.",
        "duration": 670,
        "freewheelid": "cn-2503171",
        "isclip": false,
        "typesort": "1",
        "tvratingcode": "TV-Y",
        "seriestitleid": "2503122",
        "seriesname": "Barney's World",
        "originalpremieredate": "2026-01-01T05:00:00.000Z",
        "pubdate": "2026-01-01T05:00:00.000Z",
        "expdate": "2026-10-29T03:59:00.000Z",
        "thumbnailurl": "https://i.cartoonnetwork.com/orchestrator/2503171_005_640x360.jpg",
        "authtype": "auth",
        "webflags": "",
        "tags": "cartoonito",
        "titleid": "2503171",
        "titletype": "Episode",
        "bannertext": "LATEST EPISODE",
        "originalseriesid": "2503122",
        "originalseriesname": "Barney's World",
        "hasparent": false,
        "originalpremieredateasmilliseconds": "1767243600000",
        "pubdateasmilliseconds": "1767243600000",
        "expdateasmilliseconds": "1793246340000",
        "mediaid": "70da38da2a9b34632706af0353e8c08b6fb2e4cc",
        "isunlockedfullepisode": false,
        "ismultipropertycollection": false,
        "clipsonly": false,
        "includeshortform": true
    },
    {
        "airingid": "RADS1012302500076971",
        "seasonnumber": "1",
        "seasonitemnumber": "25",
        "seriesid": "2503122",
        "id": "851d5e85ae7e174c965cf36098d4f55a76903fde",
        "collectionid": "",
        "seofriendlyurl": "/video/barney's-world/barneys-birthday-episode.html",
        "seasonepisodenumber": "25",
        "title": "Barney's Birthday",
        "episodenumber": "25",
        "type": "fullepisode",
        "active": true,
        "description": "The kids are making a quilt for Barney's birthday featuring their favorite things to do with Barney. David has a hard time choosing just one thing, so Baby Bop and Billy help him decide just in time for the party.",
        "duration": 671,
        "freewheelid": "cn-2503170",
        "isclip": false,
        "typesort": "1",
        "tvratingcode": "TV-Y",
        "seriestitleid": "2503122",
        "seriesname": "Barney's World",
        "originalpremieredate": "2026-01-01T05:00:00.000Z",
        "pubdate": "2026-01-01T05:00:00.000Z",
        "expdate": "2026-10-22T03:59:00.000Z",
        "thumbnailurl": "https://i.cartoonnetwork.com/orchestrator/2503170_010_640x360.jpg",
        "authtype": "auth",
        "webflags": "",
        "tags": "cartoonito",
        "titleid": "2503170",
        "titletype": "Episode",
        "bannertext": "LATEST EPISODE",
        "originalseriesid": "2503122",
        "originalseriesname": "Barney's World",
        "hasparent": false,
        "originalpremieredateasmilliseconds": "1767243600000",
        "pubdateasmilliseconds": "1767243600000",
        "expdateasmilliseconds": "1792641540000",
        "mediaid": "851d5e85ae7e174c965cf36098d4f55a76903fde",
        "isunlockedfullepisode": false,
        "ismultipropertycollection": false,
        "clipsonly": false,
        "includeshortform": true
    },
    {
        "airingid": "RADS1012302500076975",
        "seasonnumber": "1",
        "seasonitemnumber": "27",
        "seriesid": "2503122",
        "id": "d1a0450bb609bf0094de6c43a1b442b6dad35ae1",
        "collectionid": "",
        "seofriendlyurl": "/video/barney's-world/the-snuzzleberry-snatcher-episode.html",
        "seasonepisodenumber": "27",
        "title": "The Snuzzleberry Snatcher",
        "episodenumber": "27",
        "type": "fullepisode",
        "active": true,
        "description": "Vivie gets frustrated when her soccer ball is popped by a cactus. Barney takes the kids on an enchanted garden adventure where Vivie learns that some plants in nature are pokey for protection.",
        "duration": 671,
        "freewheelid": "cn-2503172",
        "isclip": false,
        "typesort": "1",
        "tvratingcode": "TV-Y",
        "seriestitleid": "2503122",
        "seriesname": "Barney's World",
        "originalpremieredate": "2026-01-01T05:00:00.000Z",
        "pubdate": "2026-01-01T05:00:00.000Z",
        "expdate": "2026-11-05T04:59:00.000Z",
        "thumbnailurl": "https://i.cartoonnetwork.com/orchestrator/2503172_007_640x360.jpg",
        "authtype": "auth",
        "webflags": "",
        "tags": "cartoonito",
        "titleid": "2503172",
        "titletype": "Episode",
        "bannertext": "LATEST EPISODE",
        "originalseriesid": "2503122",
        "originalseriesname": "Barney's World",
        "hasparent": false,
        "originalpremieredateasmilliseconds": "1767243600000",
        "pubdateasmilliseconds": "1767243600000",
        "expdateasmilliseconds": "1793854740000",
        "mediaid": "d1a0450bb609bf0094de6c43a1b442b6dad35ae1",
        "isunlockedfullepisode": false,
        "ismultipropertycollection": false,
        "clipsonly": false,
        "includeshortform": true
    },
    {
        "airingid": "RADS1012302500076969",
        "seasonnumber": "1",
        "seasonitemnumber": "24",
        "seriesid": "2503122",
        "id": "d3737b1ca465ef5217b9fd26185bd9e3403fa9fa",
        "collectionid": "",
        "seofriendlyurl": "/video/barney's-world/every-little-thing-episode.html",
        "seasonepisodenumber": "24",
        "title": "Every Little Thing",
        "episodenumber": "24",
        "type": "fullepisode",
        "active": true,
        "description": "The kids notice Grady is sad and Barney shows them that simple acts of kindness go a long way. Barney adds a dash of magic to the kids' actions that inspire others, allowing everyone to see the magnitude and power of simple acts of kindness.",
        "duration": 671,
        "freewheelid": "cn-2503169",
        "isclip": false,
        "typesort": "1",
        "tvratingcode": "TV-Y",
        "seriestitleid": "2503122",
        "seriesname": "Barney's World",
        "originalpremieredate": "2026-01-01T05:00:00.000Z",
        "pubdate": "2026-01-01T05:00:00.000Z",
        "expdate": "2026-10-15T03:59:00.000Z",
        "thumbnailurl": "https://i.cartoonnetwork.com/orchestrator/2503169_003_640x360.jpg",
        "authtype": "auth",
        "webflags": "",
        "tags": "cartoonito",
        "titleid": "2503169",
        "titletype": "Episode",
        "bannertext": "LATEST EPISODE",
        "originalseriesid": "2503122",
        "originalseriesname": "Barney's World",
        "hasparent": false,
        "originalpremieredateasmilliseconds": "1767243600000",
        "pubdateasmilliseconds": "1767243600000",
        "expdateasmilliseconds": "1792036740000",
        "mediaid": "d3737b1ca465ef5217b9fd26185bd9e3403fa9fa",
        "isunlockedfullepisode": false,
        "ismultipropertycollection": false,
        "clipsonly": false,
        "includeshortform": true
    },
    {
        "airingid": "RADS1012302500076977",
        "seasonnumber": "1",
        "seasonitemnumber": "28",
        "seriesid": "2503122",
        "id": "d83955f2dcc10ec1fd4b361865fffbd57d06685c",
        "collectionid": "",
        "seofriendlyurl": "/video/barney's-world/it-takes-three-episode.html",
        "seasonepisodenumber": "28",
        "title": "It Takes Three",
        "episodenumber": "28",
        "type": "fullepisode",
        "active": true,
        "description": "When Baby Bop feels left out of the kids game, she tries everything to be included. Barney uses fun, magic and empathy to help her understand that if you can't do what you want, the best thing is to find something else to enjoy.",
        "duration": 671,
        "freewheelid": "cn-2503173",
        "isclip": false,
        "typesort": "1",
        "tvratingcode": "TV-Y",
        "seriestitleid": "2503122",
        "seriesname": "Barney's World",
        "originalpremieredate": "2026-01-01T05:00:00.000Z",
        "pubdate": "2026-01-01T05:00:00.000Z",
        "expdate": "2026-11-12T04:59:00.000Z",
        "thumbnailurl": "https://i.cartoonnetwork.com/orchestrator/2503173_002_640x360.jpg",
        "authtype": "auth",
        "webflags": "",
        "tags": "cartoonito",
        "titleid": "2503173",
        "titletype": "Episode",
        "bannertext": "LATEST EPISODE",
        "originalseriesid": "2503122",
        "originalseriesname": "Barney's World",
        "hasparent": false,
        "originalpremieredateasmilliseconds": "1767243600000",
        "pubdateasmilliseconds": "1767243600000",
        "expdateasmilliseconds": "1794459540000",
        "mediaid": "d83955f2dcc10ec1fd4b361865fffbd57d06685c",
        "isunlockedfullepisode": false,
        "ismultipropertycollection": false,
        "clipsonly": false,
        "includeshortform": true
    },
    {
        "airingid": "RADS1012302500076979",
        "seasonnumber": "1",
        "seasonitemnumber": "29",
        "seriesid": "2503122",
        "id": "f8938507b8c4d1050bf45f7d7932c8c0b16e4810",
        "collectionid": "",
        "seofriendlyurl": "/video/barney's-world/the-missing-valentine-episode.html",
        "seasonepisodenumber": "29",
        "title": "The Missing Valentine",
        "episodenumber": "29",
        "type": "fullepisode",
        "active": true,
        "description": "When Barney notices that Vivie forgot to make a valentine for someone special on Valentine's Day, the kids embark on a magical quest to find out who it is. They complete challenges that help Vivie realize she forgot to make one for herself!",
        "duration": 671,
        "freewheelid": "cn-2503174",
        "isclip": false,
        "typesort": "1",
        "tvratingcode": "TV-Y",
        "seriestitleid": "2503122",
        "seriesname": "Barney's World",
        "originalpremieredate": "2026-01-01T05:00:00.000Z",
        "pubdate": "2026-01-01T05:00:00.000Z",
        "expdate": "2026-11-19T04:59:00.000Z",
        "thumbnailurl": "https://i.cartoonnetwork.com/orchestrator/2503174_006_640x360.jpg",
        "authtype": "auth",
        "webflags": "",
        "tags": "cartoonito",
        "titleid": "2503174",
        "titletype": "Episode",
        "bannertext": "LATEST EPISODE",
        "originalseriesid": "2503122",
        "originalseriesname": "Barney's World",
        "hasparent": false,
        "originalpremieredateasmilliseconds": "1767243600000",
        "pubdateasmilliseconds": "1767243600000",
        "expdateasmilliseconds": "1795064340000",
        "mediaid": "f8938507b8c4d1050bf45f7d7932c8c0b16e4810",
        "isunlockedfullepisode": false,
        "ismultipropertycollection": false,
        "clipsonly": false,
        "includeshortform": true
    }
]