{
  "airingid": "RADS1012122200051158",
  "seasonnumber": "1",
  "seasonitemnumber": "41",
  "seriesid": "433570",
  "id": "b4273d036b521b4aaa1ebc4159881f1739d85408",
  "collectionid": "",
  "seofriendlyurl": "/video/baby-looney-tunes/business-as-unusual-episode.html",
  "seasonepisodenumber": "41",
  "title": "Business as Unusual",
  "episodenumber": "41",
  "type": "fullepisode",
  "active": true,
  "description": "Bugs and Daffy open competing lemonade stands.",
  "duration": 680,
  "freewheelid": "cn-440330",
  "isclip": false,
  "typesort": "1",
  "tvratingcode": "TV-Y",
  "seriestitleid": "433570",
  "seriesname": "Baby Looney Tunes",
  "originalpremieredate": "2022-12-23T05:01:00.000Z",
  "pubdate": "2022-12-23T05:01:00.000Z",
  "expdate": "2023-01-06T04:59:00.000Z",
  "thumbnailurl": "https://i.cartoonnetwork.com/orchestrator/440330_010_640x360.jpg",
  "authtype": "unauth",
  "webflags": "",
  "tags": "cartoonito|unauth",
  "titleid": "440330",
  "titletype": "Element",
  "bannertext": "UNLOCKED",
  "originalseriesid": "433570",
  "originalseriesname": "Baby Looney Tunes",
  "hasparent": false,
  "originalpremieredateasmilliseconds": "1671771660000",
  "pubdateasmilliseconds": "1671771660000",
  "expdateasmilliseconds": "1672981140000",
  "mediaid": "b4273d036b521b4aaa1ebc4159881f1739d85408",
  "isunlockedfullepisode": true,
  "ismultipropertycollection": false,
  "clipsonly": false,
  "includeshortform": false
}